freeradical_client/__init__.py
freeradical_client/api_client.py
freeradical_client/api_response.py
freeradical_client/configuration.py
freeradical_client/exceptions.py
freeradical_client/py.typed
freeradical_client/rest.py
freeradical_client/api/__init__.py
freeradical_client/api/default_api.py
freeradical_client/models/__init__.py
freeradical_client/models/analytics_summary_get200_response.py
freeradical_client/models/login_request.py
freeradical_client/models/login_response.py
freeradical_client/models/page.py
freeradical_client/models/user.py
freeradical_client-1.0.0.dist-info/METADATA
freeradical_client-1.0.0.dist-info/WHEEL
freeradical_client-1.0.0.dist-info/top_level.txt
freeradical_client-1.0.0.dist-info/RECORD
