Metadata-Version: 2.4
Name: freeradical_client
Version: 1.0.0
Summary: FreeRadical CMS API
Home-page: https://github.com/cyberiums/freeradical
Author: FastBuilder.ai
Author-email: "FastBuilder.ai" <team@FastBuilder.ai>
Project-URL: Repository, https://github.com/cyberiums/freeradical
Keywords: OpenAPI,OpenAPI-Generator,FreeRadical CMS API
Requires-Python: >=3.9
Requires-Dist: urllib3<3.0.0,>=2.1.0
Requires-Dist: python-dateutil>=2.8.2
Requires-Dist: pydantic>=2
Requires-Dist: typing-extensions>=4.7.1
Dynamic: author
Dynamic: home-page
